eth_protocols/__init__.py
eth_protocols/logger.py
eth_protocols/camelot_v3/__init__.py
eth_protocols/camelot_v3/pool.py
eth_protocols/helpers/__init__.py
eth_protocols/helpers/dex_pairs.py
eth_protocols/helpers/multicall.py
eth_protocols/helpers/price_tracker.py
eth_protocols/tokens/__init__.py
eth_protocols/tokens/erc20/__init__.py
eth_protocols/tokens/erc20/events.py
eth_protocols/types/__init__.py
eth_protocols/types/dex_pair.py
eth_protocols/uniswap_v2/__init__.py
eth_protocols/uniswap_v2/factory.py
eth_protocols/uniswap_v2/pair.py
eth_protocols/uniswap_v2/price.py
eth_protocols/uniswap_v3/__init__.py
eth_protocols/uniswap_v3/liquidity.py
eth_protocols/uniswap_v3/pool.py
eth_protocols/utils/lookup_dict.py
eth_protocols_py-0.1.34.dist-info/METADATA
eth_protocols_py-0.1.34.dist-info/WHEEL
eth_protocols_py-0.1.34.dist-info/top_level.txt
eth_protocols_py-0.1.34.dist-info/RECORD
