Metadata-Version: 2.4
Name: eth-protocols-py
Version: 0.1.34
Requires-Python: >=3.10
Requires-Dist: eth_rpc_py
Requires-Dist: eth_typeshed_py
Requires-Dist: sortedcontainers
Requires-Dist: eth_hash
Provides-Extra: lint
Requires-Dist: mypy; extra == "lint"
Requires-Dist: ruff; extra == "lint"
Provides-Extra: test
Requires-Dist: pytest==7.4.1; extra == "test"
Requires-Dist: pytest-cov==4.1.0; extra == "test"
Requires-Dist: coverage[toml]==7.3.1; extra == "test"
Provides-Extra: build
Requires-Dist: build[virtualenv]==1.0.3; extra == "build"
Provides-Extra: dev
Requires-Dist: tox; extra == "dev"
Requires-Dist: eth-protocols-py[lint]; extra == "dev"
Requires-Dist: eth-protocols-py[test]; extra == "dev"
Requires-Dist: eth-protocols-py[build]; extra == "dev"
